<rawtrace type="eye" image="NaN.jpg" time="0" Class="" Id="" MouseClass="" MouseId="" X="512" Y="256" keys="" scroll="0" height="81" url="http://localhost:8000/downloadresearch.php" />
<rawtrace type="eye" image="NaN.jpg" time="0" Class="" Id="" MouseClass="" MouseId="" X="512" Y="256" keys="" scroll="0" height="93" url="http://localhost:8000/deleteresearch.php" />
<rawtrace type="freeze" image="NaN.jpg" time="0" Class="" Id="" MouseClass="" MouseId="" X="0" Y="0" keys="" scroll="0" height="93" url="http://localhost:8000/deleteresearch.php" />
<rawtrace type="eye" image="NaN.jpg" time="0" Class="" Id="" MouseClass="" MouseId="" X="512" Y="256" keys="" scroll="0" height="93" url="http://localhost:8000/deleteresearch.php" />
<rawtrace type="freeze" image="NaN.jpg" time="0" Class="horoscope" Id="" MouseClass="horoscope" MouseId="" X="788" Y="4191" keys="" scroll="3900" height="11373" url="https://www.globo.com/" />
<rawtrace type="eye" image="NaN.jpg" time="0" Class="" Id="" MouseClass="horoscope" MouseId="" X="847" Y="239" keys="" scroll="3900" height="11373" url="https://www.globo.com/" />
<rawtrace type="freeze" image="NaN.jpg" time="0" Class="" Id="" MouseClass="" MouseId="" X="0" Y="0" keys="" scroll="0" height="93" url="http://localhost:8000/deleteresearch.php" />
<rawtrace type="eye" image="NaN.jpg" time="0" Class="" Id="" MouseClass="" MouseId="" X="512" Y="256" keys="" scroll="0" height="81" url="http://localhost:8000/downloadresearch.php" />
<rawtrace type="eye" image="NaN.jpg" time="0" Class="" Id="" MouseClass="" MouseId="" X="512" Y="256" keys="" scroll="0" height="93" url="http://localhost:8000/deleteresearch.php" />
<rawtrace type="freeze" image="NaN.jpg" time="0" Class="" Id="" MouseClass="" MouseId="" X="0" Y="0" keys="" scroll="0" height="93" url="http://localhost:8000/deleteresearch.php" />
<rawtrace type="eye" image="NaN.jpg" time="0" Class="" Id="" MouseClass="" MouseId="" X="512" Y="256" keys="" scroll="0" height="93" url="http://localhost:8000/deleteresearch.php" />
<rawtrace type="freeze" image="NaN.jpg" time="0" Class="" Id="" MouseClass="" MouseId="" X="0" Y="0" keys="" scroll="0" height="93" url="http://localhost:8000/deleteresearch.php" />
<rawtrace type="eye" image="NaN.jpg" time="0" Class="" Id="" MouseClass="horoscope" MouseId="" X="847" Y="239" keys="" scroll="3900" height="11373" url="https://www.globo.com/" />
<rawtrace type="freeze" image="NaN.jpg" time="0" Class="" Id="" MouseClass="" MouseId="" X="0" Y="0" keys="" scroll="0" height="81" url="http://localhost:8000/downloadresearch.php" />
<rawtrace type="eye" image="NaN.jpg" time="0" Class="" Id="" MouseClass="" MouseId="" X="512" Y="256" keys="" scroll="0" height="81" url="http://localhost:8000/downloadresearch.php" />
<rawtrace type="eye" image="NaN.jpg" time="0" Class="" Id="" MouseClass="" MouseId="" X="512" Y="256" keys="" scroll="0" height="93" url="http://localhost:8000/deleteresearch.php" />
<rawtrace type="move" image="NaN.jpg" time="0" Class="" Id="" MouseClass="" MouseId="" X="0" Y="0" keys="" scroll="0" height="93" url="http://localhost:8000/deleteresearch.php" />
<rawtrace type="move" image="NaN.jpg" time="0" Class="" Id="" MouseClass="" MouseId="" X="0" Y="0" keys="" scroll="0" height="93" url="http://localhost:8000/deleteresearch.php" />
<rawtrace type="move" image="NaN.jpg" time="0" Class="" Id="" MouseClass="" MouseId="" X="0" Y="0" keys="" scroll="0" height="93" url="http://localhost:8000/deleteresearch.php" />
<rawtrace type="move" image="NaN.jpg" time="0" Class="" Id="" MouseClass="" MouseId="" X="0" Y="0" keys="" scroll="0" height="93" url="http://localhost:8000/deleteresearch.php" />
<rawtrace type="move" image="NaN.jpg" time="0" Class="" Id="" MouseClass="" MouseId="" X="0" Y="0" keys="" scroll="0" height="93" url="http://localhost:8000/deleteresearch.php" />
<rawtrace type="eye" image="NaN.jpg" time="0" Class="" Id="" MouseClass="" MouseId="" X="512" Y="256" keys="" scroll="0" height="93" url="http://localhost:8000/deleteresearch.php" />
<rawtrace type="move" image="NaN.jpg" time="0" Class="" Id="" MouseClass="" MouseId="" X="0" Y="0" keys="" scroll="0" height="93" url="http://localhost:8000/deleteresearch.php" />
<rawtrace type="move" image="NaN.jpg" time="0" Class="" Id="" MouseClass="" MouseId="" X="0" Y="0" keys="" scroll="0" height="93" url="http://localhost:8000/deleteresearch.php" />
<rawtrace type="move" image="NaN.jpg" time="0" Class="container" Id="" MouseClass="container" MouseId="" X="0" Y="0" keys="" scroll="0" height="93" url="http://localhost:8000/deleteresearch.php" />
<rawtrace type="move" image="NaN.jpg" time="0" Class="" Id="" MouseClass="" MouseId="" X="0" Y="0" keys="" scroll="0" height="93" url="http://localhost:8000/deleteresearch.php" />
<rawtrace type="move" image="NaN.jpg" time="0" Class="" Id="" MouseClass="" MouseId="" X="0" Y="0" keys="" scroll="0" height="93" url="http://localhost:8000/deleteresearch.php" />
<rawtrace type="move" image="NaN.jpg" time="0" Class="" Id="" MouseClass="" MouseId="" X="0" Y="0" keys="" scroll="0" height="93" url="http://localhost:8000/deleteresearch.php" />
<rawtrace type="move" image="NaN.jpg" time="0" Class="" Id="" MouseClass="" MouseId="" X="0" Y="0" keys="" scroll="0" height="93" url="http://localhost:8000/deleteresearch.php" />
<rawtrace type="move" image="NaN.jpg" time="0" Class="" Id="" MouseClass="" MouseId="" X="0" Y="0" keys="" scroll="0" height="93" url="http://localhost:8000/deleteresearch.php" />
<rawtrace type="move" image="NaN.jpg" time="0" Class="" Id="" MouseClass="" MouseId="" X="0" Y="0" keys="" scroll="0" height="93" url="http://localhost:8000/deleteresearch.php" />
<rawtrace type="freeze" image="NaN.jpg" time="0" Class="" Id="" MouseClass="" MouseId="" X="0" Y="0" keys="" scroll="0" height="93" url="http://localhost:8000/deleteresearch.php" />
<rawtrace type="eye" image="NaN.jpg" time="0" Class="" Id="" MouseClass="" MouseId="" X="512" Y="256" keys="" scroll="0" height="93" url="http://localhost:8000/deleteresearch.php" />
<rawtrace type="freeze" image="NaN.jpg" time="0" Class="horoscope" Id="" MouseClass="horoscope" MouseId="" X="788" Y="4191" keys="" scroll="3900" height="11373" url="https://www.globo.com/" />
<rawtrace type="eye" image="NaN.jpg" time="0" Class="" Id="" MouseClass="horoscope" MouseId="" X="847" Y="239" keys="" scroll="3900" height="11373" url="https://www.globo.com/" />
<rawtrace type="eye" image="NaN.jpg" time="0" Class="" Id="" MouseClass="" MouseId="" X="512" Y="256" keys="" scroll="0" height="81" url="http://localhost:8000/downloadresearch.php" />
<rawtrace type="freeze" image="NaN.jpg" time="0" Class="" Id="" MouseClass="" MouseId="" X="0" Y="0" keys="" scroll="0" height="93" url="http://localhost:8000/deleteresearch.php" />
<rawtrace type="eye" image="NaN.jpg" time="0" Class="" Id="" MouseClass="" MouseId="" X="512" Y="256" keys="" scroll="0" height="93" url="http://localhost:8000/deleteresearch.php" />
<rawtrace type="freeze" image="NaN.jpg" time="0" Class="" Id="" MouseClass="" MouseId="" X="0" Y="0" keys="" scroll="0" height="81" url="http://localhost:8000/downloadresearch.php" />
<rawtrace type="freeze" image="NaN.jpg" time="0" Class="" Id="" MouseClass="" MouseId="" X="0" Y="0" keys="" scroll="0" height="93" url="http://localhost:8000/deleteresearch.php" />
<rawtrace type="eye" image="NaN.jpg" time="0" Class="" Id="" MouseClass="" MouseId="" X="512" Y="256" keys="" scroll="0" height="93" url="http://localhost:8000/deleteresearch.php" />
<rawtrace type="eye" image="NaN.jpg" time="0" Class="" Id="" MouseClass="horoscope" MouseId="" X="847" Y="239" keys="" scroll="3900" height="11373" url="https://www.globo.com/" />
<rawtrace type="eye" image="NaN.jpg" time="0" Class="" Id="" MouseClass="" MouseId="" X="512" Y="256" keys="" scroll="0" height="81" url="http://localhost:8000/downloadresearch.php" />
<rawtrace type="freeze" image="NaN.jpg" time="0" Class="" Id="" MouseClass="" MouseId="" X="0" Y="0" keys="" scroll="0" height="81" url="http://localhost:8000/downloadresearch.php" />
<rawtrace type="eye" image="NaN.jpg" time="0" Class="" Id="" MouseClass="" MouseId="" X="512" Y="256" keys="" scroll="0" height="81" url="http://localhost:8000/downloadresearch.php" />
<rawtrace type="freeze" image="NaN.jpg" time="0" Class="" Id="" MouseClass="" MouseId="" X="0" Y="0" keys="" scroll="0" height="81" url="http://localhost:8000/downloadresearch.php" />
<rawtrace type="eye" image="NaN.jpg" time="0" Class="" Id="" MouseClass="" MouseId="" X="512" Y="256" keys="" scroll="0" height="81" url="http://localhost:8000/downloadresearch.php" />
<rawtrace type="eye" image="NaN.jpg" time="0" Class="" Id="" MouseClass="horoscope" MouseId="" X="847" Y="239" keys="" scroll="3900" height="11373" url="https://www.globo.com/" />
<rawtrace type="eye" image="NaN.jpg" time="0" Class="" Id="" MouseClass="" MouseId="" X="512" Y="256" keys="" scroll="0" height="93" url="http://localhost:8000/deleteresearch.php" />
<rawtrace type="freeze" image="NaN.jpg" time="0" Class="" Id="" MouseClass="" MouseId="" X="0" Y="0" keys="" scroll="0" height="81" url="http://localhost:8000/downloadresearch.php" />
<rawtrace type="eye" image="NaN.jpg" time="0" Class="" Id="" MouseClass="" MouseId="" X="512" Y="256" keys="" scroll="0" height="81" url="http://localhost:8000/downloadresearch.php" />
<rawtrace type="freeze" image="NaN.jpg" time="0" Class="" Id="" MouseClass="" MouseId="" X="0" Y="0" keys="" scroll="0" height="81" url="http://localhost:8000/downloadresearch.php" />
<rawtrace type="eye" image="NaN.jpg" time="0" Class="" Id="" MouseClass="" MouseId="" X="512" Y="256" keys="" scroll="0" height="81" url="http://localhost:8000/downloadresearch.php" />
<rawtrace type="freeze" image="NaN.jpg" time="0" Class="" Id="" MouseClass="" MouseId="" X="0" Y="0" keys="" scroll="0" height="81" url="http://localhost:8000/downloadresearch.php" />
<rawtrace type="eye" image="NaN.jpg" time="0" Class="" Id="" MouseClass="horoscope" MouseId="" X="847" Y="239" keys="" scroll="3900" height="11373" url="https://www.globo.com/" />
<rawtrace type="freeze" image="NaN.jpg" time="0" Class="" Id="" MouseClass="" MouseId="" X="0" Y="0" keys="" scroll="0" height="93" url="http://localhost:8000/deleteresearch.php" />
<rawtrace type="eye" image="NaN.jpg" time="0" Class="" Id="" MouseClass="" MouseId="" X="512" Y="256" keys="" scroll="0" height="93" url="http://localhost:8000/deleteresearch.php" />
<rawtrace type="eye" image="NaN.jpg" time="0" Class="" Id="" MouseClass="" MouseId="" X="512" Y="256" keys="" scroll="0" height="81" url="http://localhost:8000/downloadresearch.php" />
<rawtrace type="move" image="NaN.jpg" time="0" Class="" Id="" MouseClass="" MouseId="" X="0" Y="0" keys="" scroll="0" height="81" url="http://localhost:8000/downloadresearch.php" />
<rawtrace type="move" image="NaN.jpg" time="0" Class="" Id="" MouseClass="" MouseId="" X="0" Y="0" keys="" scroll="0" height="81" url="http://localhost:8000/downloadresearch.php" />
<rawtrace type="move" image="NaN.jpg" time="0" Class="" Id="" MouseClass="" MouseId="" X="0" Y="0" keys="" scroll="0" height="81" url="http://localhost:8000/downloadresearch.php" />
<rawtrace type="move" image="NaN.jpg" time="0" Class="" Id="" MouseClass="" MouseId="" X="0" Y="0" keys="" scroll="0" height="81" url="http://localhost:8000/downloadresearch.php" />
<rawtrace type="move" image="NaN.jpg" time="0" Class="" Id="" MouseClass="" MouseId="" X="0" Y="0" keys="" scroll="0" height="81" url="http://localhost:8000/downloadresearch.php" />
<rawtrace type="move" image="NaN.jpg" time="0" Class="" Id="" MouseClass="" MouseId="" X="0" Y="0" keys="" scroll="0" height="81" url="http://localhost:8000/downloadresearch.php" />
<rawtrace type="move" image="NaN.jpg" time="0" Class="" Id="" MouseClass="" MouseId="" X="0" Y="0" keys="" scroll="0" height="81" url="http://localhost:8000/downloadresearch.php" />
<rawtrace type="move" image="NaN.jpg" time="0" Class="" Id="" MouseClass="" MouseId="" X="0" Y="0" keys="" scroll="0" height="81" url="http://localhost:8000/downloadresearch.php" />
<rawtrace type="move" image="NaN.jpg" time="0" Class="" Id="" MouseClass="" MouseId="" X="0" Y="0" keys="" scroll="0" height="81" url="http://localhost:8000/downloadresearch.php" />
<rawtrace type="move" image="NaN.jpg" time="0" Class="" Id="" MouseClass="" MouseId="" X="0" Y="0" keys="" scroll="0" height="81" url="http://localhost:8000/downloadresearch.php" />
<rawtrace type="move" image="NaN.jpg" time="0" Class="" Id="" MouseClass="" MouseId="" X="0" Y="0" keys="" scroll="0" height="81" url="http://localhost:8000/downloadresearch.php" />
<rawtrace type="eye" image="NaN.jpg" time="0" Class="" Id="" MouseClass="" MouseId="" X="512" Y="256" keys="" scroll="0" height="81" url="http://localhost:8000/downloadresearch.php" />
<rawtrace type="freeze" image="NaN.jpg" time="0" Class="" Id="" MouseClass="" MouseId="" X="0" Y="0" keys="" scroll="0" height="81" url="http://localhost:8000/downloadresearch.php" />
<rawtrace type="eye" image="NaN.jpg" time="0" Class="" Id="" MouseClass="" MouseId="" X="512" Y="256" keys="" scroll="0" height="81" url="http://localhost:8000/downloadresearch.php" />
<rawtrace type="freeze" image="NaN.jpg" time="0" Class="horoscope" Id="" MouseClass="horoscope" MouseId="" X="788" Y="4191" keys="" scroll="3900" height="11373" url="https://www.globo.com/" />
<rawtrace type="eye" image="NaN.jpg" time="0" Class="" Id="" MouseClass="horoscope" MouseId="" X="847" Y="239" keys="" scroll="3900" height="11373" url="https://www.globo.com/" />
<rawtrace type="eye" image="NaN.jpg" time="0" Class="" Id="" MouseClass="" MouseId="" X="512" Y="256" keys="" scroll="0" height="93" url="http://localhost:8000/deleteresearch.php" />
<rawtrace type="freeze" image="NaN.jpg" time="0" Class="" Id="" MouseClass="" MouseId="" X="0" Y="0" keys="" scroll="0" height="81" url="http://localhost:8000/downloadresearch.php" />
<rawtrace type="eye" image="NaN.jpg" time="0" Class="" Id="" MouseClass="" MouseId="" X="512" Y="256" keys="" scroll="0" height="81" url="http://localhost:8000/downloadresearch.php" />
<rawtrace type="freeze" image="NaN.jpg" time="0" Class="" Id="" MouseClass="" MouseId="" X="0" Y="0" keys="" scroll="0" height="81" url="http://localhost:8000/downloadresearch.php" />
<rawtrace type="eye" image="NaN.jpg" time="0" Class="" Id="" MouseClass="" MouseId="" X="512" Y="256" keys="" scroll="0" height="81" url="http://localhost:8000/downloadresearch.php" />
<rawtrace type="freeze" image="NaN.jpg" time="0" Class="" Id="" MouseClass="" MouseId="" X="0" Y="0" keys="" scroll="0" height="81" url="http://localhost:8000/downloadresearch.php" />
<rawtrace type="eye" image="NaN.jpg" time="0" Class="" Id="" MouseClass="horoscope" MouseId="" X="847" Y="239" keys="" scroll="3900" height="11373" url="https://www.globo.com/" />
<rawtrace type="freeze" image="NaN.jpg" time="0" Class="" Id="" MouseClass="" MouseId="" X="0" Y="0" keys="" scroll="0" height="93" url="http://localhost:8000/deleteresearch.php" />
<rawtrace type="eye" image="NaN.jpg" time="0" Class="" Id="" MouseClass="" MouseId="" X="512" Y="256" keys="" scroll="0" height="93" url="http://localhost:8000/deleteresearch.php" />
<rawtrace type="eye" image="NaN.jpg" time="0" Class="" Id="" MouseClass="" MouseId="" X="512" Y="256" keys="" scroll="0" height="81" url="http://localhost:8000/downloadresearch.php" />
<rawtrace type="eye" image="NaN.jpg" time="0" Class="" Id="" MouseClass="" MouseId="" X="512" Y="256" keys="" scroll="0" height="81" url="http://localhost:8000/downloadresearch.php" />
<rawtrace type="move" image="NaN.jpg" time="0" Class="" Id="" MouseClass="" MouseId="" X="0" Y="0" keys="" scroll="0" height="81" url="http://localhost:8000/downloadresearch.php" />
<rawtrace type="freeze" image="NaN.jpg" time="0" Class="" Id="" MouseClass="" MouseId="" X="0" Y="0" keys="" scroll="0" height="81" url="http://localhost:8000/downloadresearch.php" />
<rawtrace type="eye" image="NaN.jpg" time="0" Class="" Id="" MouseClass="" MouseId="" X="512" Y="256" keys="" scroll="0" height="81" url="http://localhost:8000/downloadresearch.php" />
<rawtrace type="freeze" image="NaN.jpg" time="0" Class="horoscope" Id="" MouseClass="horoscope" MouseId="" X="788" Y="4191" keys="" scroll="3900" height="11373" url="https://www.globo.com/" />
<rawtrace type="eye" image="NaN.jpg" time="0" Class="" Id="" MouseClass="horoscope" MouseId="" X="847" Y="239" keys="" scroll="3900" height="11373" url="https://www.globo.com/" />
<rawtrace type="move" image="NaN.jpg" time="0" Class="" Id="" MouseClass="" MouseId="" X="0" Y="0" keys="" scroll="0" height="81" url="http://localhost:8000/downloadresearch.php" />
<rawtrace type="move" image="NaN.jpg" time="0" Class="" Id="" MouseClass="" MouseId="" X="0" Y="0" keys="" scroll="0" height="81" url="http://localhost:8000/downloadresearch.php" />
<rawtrace type="move" image="NaN.jpg" time="0" Class="" Id="" MouseClass="" MouseId="" X="0" Y="0" keys="" scroll="0" height="81" url="http://localhost:8000/downloadresearch.php" />
<rawtrace type="move" image="NaN.jpg" time="0" Class="" Id="" MouseClass="" MouseId="" X="0" Y="0" keys="" scroll="0" height="81" url="http://localhost:8000/downloadresearch.php" />
<rawtrace type="move" image="NaN.jpg" time="0" Class="" Id="" MouseClass="" MouseId="" X="0" Y="0" keys="" scroll="0" height="81" url="http://localhost:8000/downloadresearch.php" />
<rawtrace type="move" image="NaN.jpg" time="0" Class="" Id="" MouseClass="" MouseId="" X="0" Y="0" keys="" scroll="0" height="81" url="http://localhost:8000/downloadresearch.php" />
<rawtrace type="move" image="NaN.jpg" time="0" Class="" Id="" MouseClass="" MouseId="" X="0" Y="0" keys="" scroll="0" height="81" url="http://localhost:8000/downloadresearch.php" />
<rawtrace type="move" image="NaN.jpg" time="0" Class="" Id="" MouseClass="" MouseId="" X="0" Y="0" keys="" scroll="0" height="81" url="http://localhost:8000/downloadresearch.php" />
<rawtrace type="eye" image="NaN.jpg" time="0" Class="" Id="" MouseClass="" MouseId="" X="512" Y="256" keys="" scroll="0" height="81" url="http://localhost:8000/downloadresearch.php" />
<rawtrace type="freeze" image="NaN.jpg" time="0" Class="" Id="" MouseClass="" MouseId="" X="0" Y="0" keys="" scroll="0" height="81" url="http://localhost:8000/downloadresearch.php" />
<rawtrace type="eye" image="NaN.jpg" time="0" Class="" Id="" MouseClass="" MouseId="" X="512" Y="256" keys="" scroll="0" height="93" url="http://localhost:8000/deleteresearch.php" />
<rawtrace type="eye" image="NaN.jpg" time="0" Class="" Id="" MouseClass="" MouseId="" X="512" Y="256" keys="" scroll="0" height="81" url="http://localhost:8000/downloadresearch.php" />
<rawtrace type="freeze" image="NaN.jpg" time="0" Class="" Id="" MouseClass="" MouseId="" X="0" Y="0" keys="" scroll="0" height="81" url="http://localhost:8000/downloadresearch.php" />
<rawtrace type="eye" image="NaN.jpg" time="0" Class="" Id="" MouseClass="horoscope" MouseId="" X="847" Y="239" keys="" scroll="3900" height="11373" url="https://www.globo.com/" />
<rawtrace type="freeze" image="NaN.jpg" time="0" Class="" Id="" MouseClass="" MouseId="" X="0" Y="0" keys="" scroll="0" height="93" url="http://localhost:8000/deleteresearch.php" />
<rawtrace type="eye" image="NaN.jpg" time="0" Class="" Id="" MouseClass="" MouseId="" X="512" Y="256" keys="" scroll="0" height="93" url="http://localhost:8000/deleteresearch.php" />
<rawtrace type="eye" image="NaN.jpg" time="0" Class="" Id="" MouseClass="" MouseId="" X="512" Y="256" keys="" scroll="0" height="81" url="http://localhost:8000/downloadresearch.php" />
<rawtrace type="eye" image="NaN.jpg" time="0" Class="" Id="" MouseClass="" MouseId="" X="512" Y="256" keys="" scroll="0" height="81" url="http://localhost:8000/downloadresearch.php" />
<rawtrace type="freeze" image="NaN.jpg" time="0" Class="" Id="" MouseClass="" MouseId="" X="0" Y="0" keys="" scroll="0" height="81" url="http://localhost:8000/downloadresearch.php" />
<rawtrace type="eye" image="NaN.jpg" time="0" Class="" Id="" MouseClass="" MouseId="" X="512" Y="256" keys="" scroll="0" height="81" url="http://localhost:8000/downloadresearch.php" />
<rawtrace type="freeze" image="NaN.jpg" time="0" Class="horoscope" Id="" MouseClass="horoscope" MouseId="" X="788" Y="4191" keys="" scroll="3900" height="11373" url="https://www.globo.com/" />
<rawtrace type="eye" image="NaN.jpg" time="0" Class="" Id="" MouseClass="horoscope" MouseId="" X="847" Y="239" keys="" scroll="3900" height="11373" url="https://www.globo.com/" />
<rawtrace type="eye" image="NaN.jpg" time="0" Class="" Id="" MouseClass="" MouseId="" X="512" Y="256" keys="" scroll="0" height="93" url="http://localhost:8000/deleteresearch.php" />
